{
	"cmake" : 
	{
		"generator" : 
		{
			"multiConfig" : false,
			"name" : "Ninja"
		},
		"paths" : 
		{
			"cmake" : "C:/Users/olegs/AppData/Local/JetBrains/Toolbox/apps/CLion/ch-0/222.4345.21/bin/cmake/win/bin/cmake.exe",
			"cpack" : "C:/Users/olegs/AppData/Local/JetBrains/Toolbox/apps/CLion/ch-0/222.4345.21/bin/cmake/win/bin/cpack.exe",
			"ctest" : "C:/Users/olegs/AppData/Local/JetBrains/Toolbox/apps/CLion/ch-0/222.4345.21/bin/cmake/win/bin/ctest.exe",
			"root" : "C:/Users/olegs/AppData/Local/JetBrains/Toolbox/apps/CLion/ch-0/222.4345.21/bin/cmake/win/share/cmake-3.23"
		},
		"version" : 
		{
			"isDirty" : false,
			"major" : 3,
			"minor" : 23,
			"patch" : 2,
			"string" : "3.23.2",
			"suffix" : ""
		}
	},
	"objects" : 
	[
		{
			"jsonFile" : "codemodel-v2-86645f35a42d29e1961c.json",
			"kind" : "codemodel",
			"version" : 
			{
				"major" : 2,
				"minor" : 4
			}
		},
		{
			"jsonFile" : "cache-v2-dfba8274997f595c9ec2.json",
			"kind" : "cache",
			"version" : 
			{
				"major" : 2,
				"minor" : 0
			}
		},
		{
			"jsonFile" : "cmakeFiles-v1-00c3963ae906953834b2.json",
			"kind" : "cmakeFiles",
			"version" : 
			{
				"major" : 1,
				"minor" : 0
			}
		},
		{
			"jsonFile" : "toolchains-v1-d644a8fd6fbd30ee7a32.json",
			"kind" : "toolchains",
			"version" : 
			{
				"major" : 1,
				"minor" : 0
			}
		}
	],
	"reply" : 
	{
		"cache-v2" : 
		{
			"jsonFile" : "cache-v2-dfba8274997f595c9ec2.json",
			"kind" : "cache",
			"version" : 
			{
				"major" : 2,
				"minor" : 0
			}
		},
		"cmakeFiles-v1" : 
		{
			"jsonFile" : "cmakeFiles-v1-00c3963ae906953834b2.json",
			"kind" : "cmakeFiles",
			"version" : 
			{
				"major" : 1,
				"minor" : 0
			}
		},
		"codemodel-v2" : 
		{
			"jsonFile" : "codemodel-v2-86645f35a42d29e1961c.json",
			"kind" : "codemodel",
			"version" : 
			{
				"major" : 2,
				"minor" : 4
			}
		},
		"toolchains-v1" : 
		{
			"jsonFile" : "toolchains-v1-d644a8fd6fbd30ee7a32.json",
			"kind" : "toolchains",
			"version" : 
			{
				"major" : 1,
				"minor" : 0
			}
		}
	}
}
